setup.py
sauce_probability/Binomialdistribution.py
sauce_probability/Gaussiandistribution.py
sauce_probability/Generaldistribution.py
sauce_probability/__init__.py
sauce_probability.egg-info/PKG-INFO
sauce_probability.egg-info/SOURCES.txt
sauce_probability.egg-info/dependency_links.txt
sauce_probability.egg-info/not-zip-safe
sauce_probability.egg-info/top_level.txt