Metadata-Version: 1.0
Name: sauce-probability
Version: 0.1
Summary: Binomial and Gaussian Probability
Home-page: UNKNOWN
Author: Billy Hansen
Author-email: billyhansen6@gmail.com
License: UNKNOWN
Platform: UNKNOWN
